<?xml-model href="../../../../../../../temp/schema.xsd"?>

<document>
    <entry id="F-VGMDB-3274" title="Yahari Ore no Seishun Love Comedy wa Machigatteiru.">

        Contains("M-VGMDB-AL-37932-1")
        Contains("M-VGMDB-AL-51516-1")
        Contains("M-VGMDB-AL-96288-1")

        <entry id="M-VGMDB-AL-37999" title="Hello Alone / Yukino Yukinoshita (CV.Saori Hayami) & Yui Yuigahama (CV.Nao Toyama)"> <!-- generatedBy="fill_music_metadata.dart v0.1.1" -->

            Visual(VisualKind.AlbumArt, 0.3, 0.5)

            Music(0.3) {
                contributors["M-VGMDB-AL-37999-1"] = 0.5
                contributors["M-VGMDB-AL-37999-2"] = 0.5
            }

            <entry id="$-1" title="Hello Alone">
                <musicConsumedProgress length="4:39" /> <!-- generatedBy="fill_music_metadata.dart v0.1.1" --> <!-- generatedBy="fill_music_metadata.dart v0.1.1" -->

            </entry>
            <entry id="$-1" title="Hello Alone">
                <musicConsumedProgress length="4:39" /> <!-- generatedBy="fill_music_metadata.dart v0.1.1" --> <!-- generatedBy="fill_music_metadata.dart v0.1.1" -->

            </entry>
            }
        </entry>

        <entry id="M-VGMDB-AL-51394" title="Everyday World / Yukino Yukinoshita (CV.Saori Hayami) & Yui Yuigahama (CV.Nao Toyama)"> <!-- generatedBy="fill_music_metadata.dart v0.1.1" -->

            Visual(VisualKind.AlbumArt, 0.4, 0.25)

            Music(0.35) {
                contributors["M-VGMDB-AL-51394-1"] = 0.5
                contributors["M-VGMDB-AL-51394-3"] = 0.5
            }

            <entry id="$-1" title="エブリデイワールド">
                <musicConsumedProgress length="4:22" /> <!-- generatedBy="fill_music_metadata.dart v0.1.1" --> <!-- generatedBy="fill_music_metadata.dart v0.1.1" -->

            </entry>
            <entry id="$-1" title="エブリデイワールド">
                <musicConsumedProgress length="4:22" /> <!-- generatedBy="fill_music_metadata.dart v0.1.1" --> <!-- generatedBy="fill_music_metadata.dart v0.1.1" -->

            </entry>
            }
        </entry>

        <entry id="M-VGMDB-AL-96290" title="Diamond no Jundo / Yukino Yukinoshita (CV: Saori Hayami) & Yui Yuigahama (CV: Nao Toyama)"> <!-- generatedBy="fill_music_metadata.dart v0.1.1" -->

            Visual(VisualKind.AlbumArt, 0.4, 0.25)

            <entry id="$-1" title="Diamond no Jundo">
                <musicConsumedProgress length="3:27" /> <!-- generatedBy="fill_music_metadata.dart v0.1.1" --> <!-- generatedBy="fill_music_metadata.dart v0.1.1" -->
                Music(0.3)
            </entry>
        </entry>

        <!-- The Yui Depression, when I realize that the VSCC -->
        <!-- (Volunteer Service Club Compoly) is not as good as -->
        <!-- I thought to be. -->
        <!-- Read here for more details: -->
        <!-- http://yaharianalysis.x10host.com/ -->
        <!-- (esp. http://yaharianalysis.x10host.com/parts/Yui/index.php) -->
        MaxAEIPADS(5, Emotion.CU) {
            contributors["M-VGMDB-AL-51394-3"] = 0.05
            contributors["M-VGMDB-AL-37999-2"] = 0.05
            contributors["A-MAL-14813"] = 0.1
            contributors["A-MAL-23847"] = 0.8
        }

        <!-- Hikism-Yukism -->
        Politics {
            contributors["A-MAL-14813"] = 0.6
            contributors["A-MAL-23847"] = 0.4
        }

        Meme(0.7, numDays("2019-07-14" /*the July 14th incident*/, "2020-01-01")) {
            contributors["A-MAL-14813"] = 0.4
            contributors["A-MAL-23847"] = 0.6
        }

        <!-- VSCC is pretty comfy (before Yui Depression) -->
        NEI(0.6, Emotion.MP) {
            contributors["A-MAL-14813"] = 0.3
            contributors["A-MAL-23847"] = 0.7
        }

        <!-- https://github.com/ngoduyanh/nrs-impl-kt/issues/285 -->
        <!-- tldr -->
        <!-- yui was gonna be waifu but yui depression etc etc -->
        WaifuUnknownPeriod("Yui Yuigahama", 30) {
            contributors["A-MAL-14813"] = 0.1
            contributors["A-MAL-23847"] = 0.9
        }

        <entry id="A-MAL-14813" title="Yahari Ore no Seishun Love Comedy wa Machigatteiru."> <!-- generatedBy="fill_anime_metadata.dart v0.1.1" -->
            <source>
                <adb id="14813"/>
                <ks id="7169"/>
                <al id="14813"/>
                <mal id="14813"/>
            </source>

            <!-- Brain's Base drew Yukino better than Yui -->
            <bestGirl name="Yukino Yukinoshita" /> <!-- generatedBy="generate_best_girls.dart v0.1.0" -->

            Visual(VisualKind.Animated, 0.25, 0.4)
            NEI(0.75, Emotion.AP)

            <featureMusic id="M-VGMDB-AL-37932-1" />
            <featureMusic id="M-VGMDB-AL-37999" />

            AnimeConsumedProgress(EntryStatus.Completed, 1.0, 13)
        </entry>

        <entry id="A-MAL-23847" title="Yahari Ore no Seishun Love Comedy wa Machigatteiru. Zoku"> <!-- generatedBy="fill_anime_metadata.dart v0.1.1" -->
            <source>
                <adb id="23847"/>
                <ks id="8478"/>
                <al id="20698"/>
                <mal id="23847"/>
            </source>

            <!-- feel. drew Yui better -->
            <bestGirl name="Yui Yuigahama" /> <!-- generatedBy="generate_best_girls.dart v0.1.0" -->

            Visual(VisualKind.Animated, 0.4, 0.25)
            NEI(0.25, Emotion.AP)

            <!-- Oregairu S2 has a lot of drama that I don't even -->
            <!-- understand. But it's pretty good ngl. -->
            <!-- (basically atmospheric-CU farm) -->
            AEI(0.9, Emotion.CU)

            <featureMusic id="M-VGMDB-AL-51516-1" />
            <featureMusic id="M-VGMDB-AL-51394-1" />
            <featureMusic id="M-VGMDB-AL-51394-3" />

            AnimeConsumedProgress(EntryStatus.Completed, 1.0, 13)
        </entry>

        <entry id="A-MAL-39547" title="Yahari Ore no Seishun Love Comedy wa Machigatteiru. Kan"> <!-- generatedBy="fill_anime_metadata.dart v0.1.1" -->
            <source>
                <adb id="39547"/>
                <ks id="42194"/>
                <al id="108489"/>
                <mal id="39547"/>
            </source>

            <bestGirl name="Yui Yuigahama" /> <!-- generatedBy="generate_best_girls.dart v0.1.0" -->
            seasonal = true

            Visual(VisualKind.Animated, 0.4, 0.25)
            Meme(0.2, 2)

            <!-- Yui dead people arc was kinda good -->
            <!-- but Oregairu is just dead -->
            <!-- you can't do much about it -->
            AEI(0.4, Emotion.CU)
            NEI(0.1, Emotion.AP)

            <!-- killed by lapis re lights lmao xd -->
            KilledBy("A-MAL-37587", potential = 0.75, effect = 0.5)

            <featureMusic id="M-VGMDB-AL-96288-1" />
            <featureMusic id="M-VGMDB-AL-96290-1" />

            AnimeConsumedProgress(EntryStatus.Completed, 1.0, 12)
        </entry>
    </entry>
</document>
